jtb/__init__.py
jtb/jupyter.py
jtb-0.0.2.dist-info/LICENSE
jtb-0.0.2.dist-info/WHEEL
jtb-0.0.2.dist-info/METADATA
jtb-0.0.2.dist-info/RECORD
